atari_8_bit_utils/__about__.py
atari_8_bit_utils/__init__.py
atari_8_bit_utils/a8utils.py
atari_8_bit_utils/atascii.py
atari_8_bit_utils/behavior.py
atari_8_bit_utils/sync.py
atari_8_bit_utils/tree.py
atari_8_bit_utils-0.2.8.dist-info/METADATA
atari_8_bit_utils-0.2.8.dist-info/WHEEL
atari_8_bit_utils-0.2.8.dist-info/entry_points.txt
atari_8_bit_utils-0.2.8.dist-info/licenses/LICENSE
atari_8_bit_utils-0.2.8.dist-info/RECORD
